{"inkVersion":21,"root":[["^Awilda: Let's stop here for a bit.","\n",["ev",{"^->":"0.2.$r1"},{"temp=":"$r"},"str",{"->":".^.s"},[{"#n":"$r1"}],"/str","/ev",{"*":"0.c-0","flg":18},{"s":["^You: That's a brilliant idea!",{"->":"$r","var":true},null]}],["ev",{"^->":"0.3.$r1"},{"temp=":"$r"},"str",{"->":".^.s"},[{"#n":"$r1"}],"/str","/ev",{"*":"0.c-1","flg":18},{"s":["^You: Should we maybe travel a bit farther?",{"->":"$r","var":true},null]}],{"c-0":["ev",{"^->":"0.c-0.$r2"},"/ev",{"temp=":"$r"},{"->":"0.2.s"},[{"#n":"$r2"}],"\n",{"->":"0.g-0"},{"#f":5}],"c-1":["ev",{"^->":"0.c-1.$r2"},"/ev",{"temp=":"$r"},{"->":"0.3.s"},[{"#n":"$r2"}],"\n","^Awilda: No, I think we really should rest.","\n",{"->":"0.g-0"},{"#f":5}],"g-0":["^Captain Krill: Hey!!!","\n","^Captain Krill: This is my territory and you need to leave immediately.","\n",["ev",{"^->":"0.g-0.4.$r1"},{"temp=":"$r"},"str",{"->":".^.s"},[{"#n":"$r1"}],"/str","/ev",{"*":".^.^.c-2","flg":18},{"s":["^You: Please let us rest for a moment, we are exhausted.",{"->":"$r","var":true},null]}],["ev",{"^->":"0.g-0.5.$r1"},{"temp=":"$r"},"str",{"->":".^.s"},[{"#n":"$r1"}],"/str","/ev",{"*":".^.^.c-3","flg":18},{"s":["^You: Make us",{"->":"$r","var":true},null]}],{"c-2":["ev",{"^->":"0.g-0.c-2.$r2"},"/ev",{"temp=":"$r"},{"->":".^.^.4.s"},[{"#n":"$r2"}],"\n","^Captain Krill: Not on my land!","\n","^You: Okay. We'll leave.","\n","^Awilda: Like hell we will! This isn't your turf.","\n",{"->":"0.g-1"},{"#f":5}],"c-3":["ev",{"^->":"0.g-0.c-3.$r2"},"/ev",{"temp=":"$r"},{"->":".^.^.5.s"},[{"#n":"$r2"}],"\n",{"->":"0.g-1"},{"#f":5}],"#f":5}],"g-1":["^Captain Krill: I was hoping you'd say that. Prepare for battle!!","\n","end",["done",{"#f":5,"#n":"g-2"}],{"#f":5}]}],"done",{"#f":1}],"listDefs":{}}